pathao_api/__init__.py
pathao_courier_api-1.0.0.dist-info/LICENSE
pathao_courier_api-1.0.0.dist-info/METADATA
pathao_courier_api-1.0.0.dist-info/WHEEL
pathao_courier_api-1.0.0.dist-info/top_level.txt
pathao_courier_api-1.0.0.dist-info/RECORD
