Metadata-Version: 2.1
Name: pathao-courier-api
Version: 1.0.0
Summary: Api client for Pathao Courier API
Author: Omar Faruk Riyad
Author-email: <omfriyad@gmail.com>
Keywords: python,pathao,courier,api
Classifier: Programming Language :: Python
Classifier: Programming Language :: Python :: 3
Classifier: Programming Language :: Python :: 3.7
Classifier: Programming Language :: Python :: 3.8
Classifier: Programming Language :: Python :: 3.9
Classifier: Programming Language :: Python :: 3.10
Classifier: Operating System :: OS Independent
License-File: LICENSE
